ecactus/__init__.py
ecactus/async_client.py
ecactus/base.py
ecactus/client.py
ecactus/exceptions.py
ecactus/model.py
ecactus_ecos_py-0.2.1.dist-info/licenses/LICENSE
ecactus_ecos_py-0.2.1.dist-info/METADATA
ecactus_ecos_py-0.2.1.dist-info/WHEEL
ecactus_ecos_py-0.2.1.dist-info/top_level.txt
ecactus_ecos_py-0.2.1.dist-info/RECORD
