Metadata-Version: 2.4
Name: ecactus-ecos-py
Version: 0.2.1
Summary: Python client library for eCactus ECOS API
Author-email: Germain Masse <g-dev@masse.me>
License: GPL-3.0-only
Project-URL: Homepage, https://github.com/gmasse/ecactus-ecos-py
Project-URL: Documentation, https://g.masse.me/ecactus-ecos-py/
Project-URL: Repository, https://github.com/gmasse/ecactus-ecos-py.git
Keywords: api-client,ecactus,ecos,weiheng,energy-management,solar-panels,battery-management-system
Classifier: Development Status :: 4 - Beta
Classifier: Intended Audience :: Developers
Classifier: Operating System :: OS Independent
Classifier: Programming Language :: Python :: 3
Classifier: Topic :: Home Automation
Requires-Python: >=3.11
License-File: LICENSE
Requires-Dist: requests>=2.32.3
Requires-Dist: aiohttp>=3.10.10
Requires-Dist: pydantic>=2.10.6
Provides-Extra: dev
Requires-Dist: ruff==0.9.1; extra == "dev"
Requires-Dist: mypy==1.14.1; extra == "dev"
Requires-Dist: pytest==8.3.4; extra == "dev"
Requires-Dist: pytest-asyncio==0.25.2; extra == "dev"
Requires-Dist: pytest-cov==6.0.0; extra == "dev"
Requires-Dist: mkdocs==1.6.1; extra == "dev"
Requires-Dist: mkdocs-material==9.5.50; extra == "dev"
Requires-Dist: mkdocstrings==0.28.1; extra == "dev"
Requires-Dist: mkdocstrings-python==1.16.1; extra == "dev"
Requires-Dist: python-dateutil==2.9.0.post0; extra == "dev"
Dynamic: license-file
